difference_finder/__init__.py
difference_finder/data.py
difference_finder/finder.py
difference_finder/logger.py
difference_finder/metrics.py
difference_finder/processor.py
difference_finder/strategy.py
difference_finder/utils.py
difference_finder-0.0.4.dist-info/METADATA
difference_finder-0.0.4.dist-info/WHEEL
difference_finder-0.0.4.dist-info/top_level.txt
difference_finder-0.0.4.dist-info/RECORD
