Metadata-Version: 2.1
Name: difference-finder
Version: 0.0.4
Summary: Find difference between two images using pytorch.
Home-page: https://github.com/jeongsol-kim/difference_finder
Author: Jeongsol Kim
Author-email: wjdthf3927@gmail.com
License: MIT
Classifier: Programming Language :: Python :: 3
Classifier: License :: OSI Approved :: MIT License
Classifier: Operating System :: OS Independent
Requires-Dist: numpy
Requires-Dist: Pillow
Requires-Dist: rich
Requires-Dist: torch
Requires-Dist: torchvision
Requires-Dist: lpips
Requires-Dist: pytorch-msssim
